nextplot/__about__.py
nextplot/__init__.py
nextplot/cluster.py
nextplot/common.py
nextplot/geojson.py
nextplot/main.py
nextplot/osrm.py
nextplot/point.py
nextplot/progression.py
nextplot/route.py
nextplot/routingkit.py
nextplot/test.py
nextplot/types.py
nextplot-0.1.9.dist-info/METADATA
nextplot-0.1.9.dist-info/WHEEL
nextplot-0.1.9.dist-info/entry_points.txt
nextplot-0.1.9.dist-info/licenses/LICENSE
nextplot-0.1.9.dist-info/RECORD
