Metadata-Version: 2.4
Name: nextplot
Version: 0.1.9
Summary: Tools for plotting routes, clusters and more from JSON
Project-URL: Homepage, https://www.nextmv.io
Project-URL: Documentation, https://github.com/nextmv-io/nextplot
Project-URL: Repository, https://github.com/nextmv-io/nextplot
Author-email: Nextmv <tech@nextmv.io>
Maintainer-email: Nextmv <tech@nextmv.io>
License:                                  Apache License
License-File: LICENSE
Keywords: clustering,geospatial,locations,operations research,vehicle routing,visualization
Classifier: License :: OSI Approved :: Apache Software License
Classifier: Operating System :: OS Independent
Classifier: Programming Language :: Python :: 3
Requires-Python: >=3.10
Requires-Dist: argcomplete>=2.0.0
Requires-Dist: colorutils>=0.3.0
Requires-Dist: folium>=0.17.0
Requires-Dist: jsonpath-ng>=1.5.3
Requires-Dist: kaleido>=0.2.1
Requires-Dist: numpy>=1.22.3
Requires-Dist: plotly>=5.7.0
Requires-Dist: polyline>=2.0.2
Requires-Dist: scipy>=1.8.0
